{
  "hash": "7fa6a0ed",
  "configHash": "c05c6715",
  "lockfileHash": "a1c42aa6",
  "browserHash": "927bc69b",
  "optimized": {
    "@vue/devtools-api": {
      "src": "../../../../node_modules/@vue/devtools-api/lib/esm/index.js",
      "file": "@vue_devtools-api.js",
      "fileHash": "0fc047e9",
      "needsInterop": false
    },
    "@vuepress/shared": {
      "src": "../../../../node_modules/@vuepress/shared/dist/index.js",
      "file": "@vuepress_shared.js",
      "fileHash": "b63e1f26",
      "needsInterop": false
    },
    "vue": {
      "src": "../../../../node_modules/vue/dist/vue.runtime.esm-bundler.js",
      "file": "vue.js",
      "fileHash": "a3168341",
      "needsInterop": false
    },
    "vue-router": {
      "src": "../../../../node_modules/vue-router/dist/vue-router.esm-bundler.js",
      "file": "vue-router.js",
      "fileHash": "8c01eec8",
      "needsInterop": false
    },
    "@theme/useDarkMode": {
      "src": "../../../../node_modules/@vuepress/theme-default/lib/client/composables/useDarkMode.js",
      "file": "@theme_useDarkMode.js",
      "fileHash": "2b6c916c",
      "needsInterop": false
    },
    "@theme/useScrollPromise": {
      "src": "../../../../node_modules/@vuepress/theme-default/lib/client/composables/useScrollPromise.js",
      "file": "@theme_useScrollPromise.js",
      "fileHash": "7e9ae58a",
      "needsInterop": false
    },
    "@theme/useSidebarItems": {
      "src": "../../../../node_modules/@vuepress/theme-default/lib/client/composables/useSidebarItems.js",
      "file": "@theme_useSidebarItems.js",
      "fileHash": "163711df",
      "needsInterop": false
    },
    "@theme/useThemeData": {
      "src": "../../../../node_modules/@vuepress/theme-default/lib/client/composables/useThemeData.js",
      "file": "@theme_useThemeData.js",
      "fileHash": "e555b879",
      "needsInterop": false
    },
    "@theme/useUpdateDeviceStatus": {
      "src": "../../../../node_modules/@vuepress/theme-default/lib/client/composables/useUpdateDeviceStatus.js",
      "file": "@theme_useUpdateDeviceStatus.js",
      "fileHash": "a9b76455",
      "needsInterop": false
    },
    "@theme/useNavigate": {
      "src": "../../../../node_modules/@vuepress/theme-default/lib/client/composables/useNavigate.js",
      "file": "@theme_useNavigate.js",
      "fileHash": "76cc0cdd",
      "needsInterop": false
    },
    "@theme/useRelatedLinks": {
      "src": "../../../../node_modules/@vuepress/theme-default/lib/client/composables/useRelatedLinks.js",
      "file": "@theme_useRelatedLinks.js",
      "fileHash": "d7f3e3d6",
      "needsInterop": false
    },
    "@theme/useNavbarConfig": {
      "src": "../../../../node_modules/@vuepress/theme-default/lib/client/composables/useNavbarConfig.js",
      "file": "@theme_useNavbarConfig.js",
      "fileHash": "4f7c04e3",
      "needsInterop": false
    },
    "@theme/useNavbarRepo": {
      "src": "../../../../node_modules/@vuepress/theme-default/lib/client/composables/useNavbarRepo.js",
      "file": "@theme_useNavbarRepo.js",
      "fileHash": "2b0c508d",
      "needsInterop": false
    },
    "@theme/useNavbarSelectLanguage": {
      "src": "../../../../node_modules/@vuepress/theme-default/lib/client/composables/useNavbarSelectLanguage.js",
      "file": "@theme_useNavbarSelectLanguage.js",
      "fileHash": "4fbd4b0f",
      "needsInterop": false
    },
    "@theme/useContributors": {
      "src": "../../../../node_modules/@vuepress/theme-default/lib/client/composables/useContributors.js",
      "file": "@theme_useContributors.js",
      "fileHash": "e0246ee3",
      "needsInterop": false
    },
    "@theme/useEditLink": {
      "src": "../../../../node_modules/@vuepress/theme-default/lib/client/composables/useEditLink.js",
      "file": "@theme_useEditLink.js",
      "fileHash": "aabf6424",
      "needsInterop": false
    },
    "@theme/useLastUpdated": {
      "src": "../../../../node_modules/@vuepress/theme-default/lib/client/composables/useLastUpdated.js",
      "file": "@theme_useLastUpdated.js",
      "fileHash": "5b2fc22d",
      "needsInterop": false
    }
  },
  "chunks": {
    "chunk-UKCZNIRO": {
      "file": "chunk-UKCZNIRO.js"
    },
    "chunk-HF5MB2VA": {
      "file": "chunk-HF5MB2VA.js"
    },
    "chunk-VNGGDC5Q": {
      "file": "chunk-VNGGDC5Q.js"
    },
    "chunk-K7GDBC4F": {
      "file": "chunk-K7GDBC4F.js"
    },
    "chunk-U3KLAJNM": {
      "file": "chunk-U3KLAJNM.js"
    },
    "chunk-RY5ODQAQ": {
      "file": "chunk-RY5ODQAQ.js"
    },
    "chunk-S2KHOG74": {
      "file": "chunk-S2KHOG74.js"
    }
  }
}